pykvs_lite/__init__.py
pykvs_lite/pykvs_lite.py
pykvs_lite-0.1.8.dist-info/LICENSE
pykvs_lite-0.1.8.dist-info/METADATA
pykvs_lite-0.1.8.dist-info/WHEEL
pykvs_lite-0.1.8.dist-info/top_level.txt
pykvs_lite-0.1.8.dist-info/RECORD
