Metadata-Version: 2.1
Name: pykvs-lite
Version: 0.1.8
Summary: Simple and convenient Key-value Store Library
Home-page: https://github.com/kujirahand/pykvs_lite
Author: kujirahand
Author-email: web@kujirahand.com
Maintainer: kujirahand
Maintainer-email: web@kujirahand.com
License: MIT
Platform: UNKNOWN
Classifier: Programming Language :: Python :: 3
